matrix_reminder_bot/__init__.py
matrix_reminder_bot/bot_commands.py
matrix_reminder_bot/callbacks.py
matrix_reminder_bot/config.py
matrix_reminder_bot/errors.py
matrix_reminder_bot/functions.py
matrix_reminder_bot/main.py
matrix_reminder_bot/reminder.py
matrix_reminder_bot/storage.py
matrix_reminder_bot-0.4.0.data/scripts/matrix-reminder-bot
matrix_reminder_bot-0.4.0.dist-info/licenses/LICENSE
matrix_reminder_bot-0.4.0.dist-info/METADATA
matrix_reminder_bot-0.4.0.dist-info/WHEEL
matrix_reminder_bot-0.4.0.dist-info/top_level.txt
matrix_reminder_bot-0.4.0.dist-info/RECORD
