Metadata-Version: 2.4
Name: matrix-reminder-bot
Version: 0.4.0
Summary: A matrix bot to remind you about things!
Home-page: https://github.com/anoadragon453/matrix-reminder-bot
Classifier: License :: OSI Approved :: Apache Software License
Classifier: Programming Language :: Python :: 3 :: Only
Classifier: Programming Language :: Python :: 3.8
Classifier: Programming Language :: Python :: 3.9
Classifier: Programming Language :: Python :: 3.10
Classifier: Programming Language :: Python :: 3.11
Classifier: Programming Language :: Python :: 3.12
License-File: LICENSE
Requires-Dist: matrix-nio[e2e]>=0.24.0
Requires-Dist: Markdown>=3.5.2
Requires-Dist: PyYAML>=6.0.1
Requires-Dist: dateparser>=1.2.0
Requires-Dist: readabledelta>=0.0.2
Requires-Dist: apscheduler>=3.10.4
Requires-Dist: pytz>=2024.1
Requires-Dist: arrow>=1.3.0
Requires-Dist: pretty_cron>=1.2.0
Provides-Extra: postgres
Requires-Dist: psycopg2>=2.9.9; extra == "postgres"
Provides-Extra: dev
Requires-Dist: isort==6.0.1; extra == "dev"
Requires-Dist: flake8==7.3.0; extra == "dev"
Requires-Dist: flake8-comprehensions==3.17.0; extra == "dev"
Requires-Dist: black==25.9.0; extra == "dev"
Dynamic: classifier
Dynamic: description
Dynamic: description-content-type
Dynamic: home-page
Dynamic: license-file
Dynamic: provides-extra
Dynamic: requires-dist
Dynamic: summary
